pachypy/__init__.py
pachypy/adapter.py
pachypy/client.py
pachypy/pretty.py
pachypy/registry.py
pachypy/utils.py
pachypy-0.1.7.dist-info/LICENSE
pachypy-0.1.7.dist-info/METADATA
pachypy-0.1.7.dist-info/WHEEL
pachypy-0.1.7.dist-info/top_level.txt
pachypy-0.1.7.dist-info/RECORD
