Metadata-Version: 2.1
Name: pachypy
Version: 0.1.7
Summary: Python client library for Pachyderm
Home-page: https://github.com/itssimon/pachypy
Author: Simon Gurcke
License: UNKNOWN
Platform: UNKNOWN
Classifier: Development Status :: 3 - Alpha
Classifier: Programming Language :: Python :: 3 :: Only
Classifier: Operating System :: OS Independent
Classifier: License :: OSI Approved :: Apache Software License
Requires-Dist: boto3 (>=1.9.119)
Requires-Dist: croniter (>=0.3.29)
Requires-Dist: docker (>=3.7.2)
Requires-Dist: ipython (>=7.4.0)
Requires-Dist: Jinja2 (>=2.10.1)
Requires-Dist: pandas (>=0.24.2)
Requires-Dist: python-pachyderm (>=1.9.0.post4)
Requires-Dist: pytz (>=2018.9)
Requires-Dist: pyyaml (>=3.13)
Requires-Dist: termcolor (>=1.1.0)
Requires-Dist: tqdm (>=4.31.1)
Requires-Dist: tzlocal (>=1.5.1)
Provides-Extra: docs
Requires-Dist: sphinx (>=2.0.0) ; extra == 'docs'
Requires-Dist: sphinx-autodoc-typehints (>=1.6.0) ; extra == 'docs'
Requires-Dist: sphinx-rtd-theme (>=0.4.3) ; extra == 'docs'
Provides-Extra: test
Requires-Dist: pytest (>=4.3.1) ; extra == 'test'
Requires-Dist: pytest-cov (>=2.6.1) ; extra == 'test'
